LICENSE
MANIFEST.in
README.md
requirements.txt
setup.cfg
setup.py
fono/ReferenceModel.py
fono/__init__.py
fono/run.py
fono/solve.py
fono/version.py
fono.egg-info/PKG-INFO
fono.egg-info/SOURCES.txt
fono.egg-info/dependency_links.txt
fono.egg-info/entry_points.txt
fono.egg-info/requires.txt
fono.egg-info/top_level.txt
fono/data/__init__.py
fono/data/__init__.pyc
fono/data/price.csv
fono/data/quantity.csv
fono/data/shipping.csv