Metadata-Version: 1.0
Name: fono
Version: 0.2.8
Summary: A python package to find optimal number of orders
Home-page: https://github.com/kdheepak89/fono
Author: Dheepak Krishnamurthy
Author-email: kdheepak89@gmail.com
License: Revised BSD License
Platform: UNKNOWN
